agentic_sdlc/__init__.py
agentic_sdlc/cli.py
agentic_sdlc/core/__init__.py
agentic_sdlc/core/brain/__init__.py
agentic_sdlc/core/brain/brain_cli.py
agentic_sdlc/core/brain/demand_runner.py
agentic_sdlc/core/brain/state_manager.py
agentic_sdlc/core/cli/main.py
agentic_sdlc/core/utils/artifact_manager.py
agentic_sdlc/core/utils/common.py
agentic_sdlc/core/utils/console.py
agentic_sdlc/core/utils/kb_manager.py
agentic_sdlc/defaults/GEMINI.md
agentic_sdlc/defaults/README.md
agentic_sdlc/defaults/__init__.py
agentic_sdlc/defaults/env.template
agentic_sdlc/defaults/demands/example-daily-check.md
agentic_sdlc/defaults/ide-integration/INTEGRATION-SUMMARY.md
agentic_sdlc/defaults/ide-integration/KIRO-IDE.md
agentic_sdlc/defaults/ide-integration/README.md
agentic_sdlc/defaults/rules/agent-execution.md
agentic_sdlc/defaults/rules/ai-enforcement.md
agentic_sdlc/defaults/rules/artifacts.md
agentic_sdlc/defaults/rules/auto-learning.md
agentic_sdlc/defaults/rules/code-quality.md
agentic_sdlc/defaults/rules/folder-structure.md
agentic_sdlc/defaults/rules/git-workflow.md
agentic_sdlc/defaults/rules/global.md
agentic_sdlc/defaults/rules/naming-conventions.md
agentic_sdlc/defaults/rules/skills.md
agentic_sdlc/defaults/skills/role-ba.md
agentic_sdlc/defaults/skills/role-brain.md
agentic_sdlc/defaults/skills/role-cloud.md
agentic_sdlc/defaults/skills/role-dev.md
agentic_sdlc/defaults/skills/role-devops.md
agentic_sdlc/defaults/skills/role-game.md
agentic_sdlc/defaults/skills/role-mobile.md
agentic_sdlc/defaults/skills/role-orchestrator.md
agentic_sdlc/defaults/skills/role-pm.md
agentic_sdlc/defaults/skills/role-po.md
agentic_sdlc/defaults/skills/role-reporter.md
agentic_sdlc/defaults/skills/role-research.md
agentic_sdlc/defaults/skills/role-sa.md
agentic_sdlc/defaults/skills/role-seca.md
agentic_sdlc/defaults/skills/role-stakeholder.md
agentic_sdlc/defaults/skills/role-tester.md
agentic_sdlc/defaults/skills/role-uiux.md
agentic_sdlc/defaults/skills/ba/SKILL.md
agentic_sdlc-2.7.5.dist-info/licenses/LICENSE
agentic_sdlc-2.7.5.dist-info/METADATA
agentic_sdlc-2.7.5.dist-info/WHEEL
agentic_sdlc-2.7.5.dist-info/entry_points.txt
agentic_sdlc-2.7.5.dist-info/top_level.txt
agentic_sdlc-2.7.5.dist-info/RECORD
