Metadata-Version: 2.4
Name: agentic-sdlc
Version: 2.7.5
Summary: AI-powered SDLC framework with self-learning brain, automated workflows, and intelligent knowledge management
Author-email: Dao Quang Truong <truongnat@gmail.com>
License: MIT
Project-URL: Homepage, https://github.com/truongnat/agentic-sdlc
Project-URL: Documentation, https://github.com/truongnat/agentic-sdlc#readme
Project-URL: Repository, https://github.com/truongnat/agentic-sdlc
Project-URL: Issues, https://github.com/truongnat/agentic-sdlc/issues
Keywords: ai,sdlc,workflow,automation,agent,brain,knowledge-management,kit,sdk
Classifier: Development Status :: 4 - Beta
Classifier: Intended Audience :: Developers
Classifier: License :: OSI Approved :: MIT License
Classifier: Programming Language :: Python :: 3
Classifier: Programming Language :: Python :: 3.10
Classifier: Programming Language :: Python :: 3.11
Classifier: Programming Language :: Python :: 3.12
Classifier: Topic :: Software Development :: Libraries :: Python Modules
Classifier: Topic :: Software Development :: Quality Assurance
Requires-Python: >=3.10
License-File: LICENSE
Requires-Dist: click>=8.1.0
Requires-Dist: rich>=13.0.0
Requires-Dist: pydantic>=2.0.0
Requires-Dist: python-dotenv>=1.0.0
Requires-Dist: requests>=2.31.0
Requires-Dist: PyGithub>=2.1.1
Requires-Dist: openai>=1.0.0
Requires-Dist: anthropic>=0.7.0
Requires-Dist: streamlit>=1.28.0
Requires-Dist: PyYAML>=6.0
Requires-Dist: dspy-ai>=2.1.0
Requires-Dist: docker>=6.1.0
Requires-Dist: googlesearch-python>=1.2.0
Requires-Dist: autogen-agentchat
Provides-Extra: dev
Requires-Dist: pytest>=7.4.0; extra == "dev"
Requires-Dist: pytest-cov>=4.1.0; extra == "dev"
Requires-Dist: black>=23.0.0; extra == "dev"
Requires-Dist: ruff>=0.1.0; extra == "dev"
Requires-Dist: mypy>=1.5.0; extra == "dev"
Provides-Extra: graph
Requires-Dist: neo4j>=5.14.0; extra == "graph"
Provides-Extra: mcp
Requires-Dist: tavily-python>=0.3.0; extra == "mcp"
Requires-Dist: brave-search>=1.0.0; extra == "mcp"
Dynamic: license-file
